.gitignore
LICENSE
README.md
setup.py
.github/workflows/pypi_publish.yaml
bf16_fused_adam/__init__.py
bf16_fused_adam/adamw.py
bf16_fused_adam/adamw_test.py
bf16_fused_adam/triton_ops.py
bf16_fused_adam.egg-info/PKG-INFO
bf16_fused_adam.egg-info/SOURCES.txt
bf16_fused_adam.egg-info/dependency_links.txt
bf16_fused_adam.egg-info/top_level.txt
csrc/bf16_fused_adam.cu
csrc/bf16_fused_adam.h
csrc/ops.cu