Metadata-Version: 2.1
Name: bf16_fused_adam
Version: 0.1
Summary: BFloat16 Fused Adam Optimizer
Home-page: https://github.com/imoneoi/bf16_fused_adam
Author: One
Author-email: imonenext@gmail.com
Classifier: Programming Language :: Python :: 3
Classifier: License :: OSI Approved :: Apache Software License
Classifier: Operating System :: Unix
License-File: LICENSE
